omuplugin_marshmallow/__init__.py
omuplugin_marshmallow/const.py
omuplugin_marshmallow/plugin.py
omuplugin_marshmallow/types.py
omuplugin_marshmallow/version.py
omuplugin_marshmallow-0.9.13.dist-info/METADATA
omuplugin_marshmallow-0.9.13.dist-info/WHEEL
omuplugin_marshmallow-0.9.13.dist-info/entry_points.txt
omuplugin_marshmallow-0.9.13.dist-info/RECORD
