Metadata-Version: 2.4
Name: omuplugin_marshmallow
Version: 0.9.13
Summary: マシュマロのメッセージを取得するためのOMUAPPSプラグイン
Author-email: am230 <111672334+am230@users.noreply.github.com>
Requires-Python: >=3.12
Requires-Dist: loguru>=0.7.2
Requires-Dist: marshmallowqa-py>=0.7.2
Requires-Dist: omu>=0.9.13
Requires-Dist: rookiepy>=0.5.3
